.gitignore
.gitmodules
LICENSE.txt
MANIFEST.in
README.rst
TODO.rst
pytest.ini
requirements.txt
setup.py
doc/Makefile
doc/source/conf.py
doc/source/history.rst
doc/source/index.rst
doc/source/introduction.rst
doc/source/tutorial-advanced.rst
doc/source/tutorial-basic.rst
doc/source/tutorial-modules.rst
doc/source/_templates/layout.html
doc/source/api/cluda.rst
doc/source/api/computations.rst
doc/source/api/core.rst
doc/source/api/helpers.rst
doc/source/api/index.rst
doc/source/api/transformations.rst
doc/source/api/version.rst
examples/demo_fftn_with_transpose.py
examples/demo_fftshift_transformation.py
examples/demo_real_to_complex_fft.py
examples/demo_specgram.py
examples/demo_specialized_fft.mako
examples/demo_specialized_fft.py
examples/demo_struct_reduce.py
examples/demo_tempalloc.py
reikna/__init__.py
reikna/dht.py
reikna/transformations.py
reikna/version.py
reikna.egg-info/PKG-INFO
reikna.egg-info/SOURCES.txt
reikna.egg-info/dependency_links.txt
reikna.egg-info/requires.txt
reikna.egg-info/top_level.txt
reikna/algorithms/__init__.py
reikna/algorithms/predicates.py
reikna/algorithms/pureparallel.py
reikna/algorithms/reduce.mako
reikna/algorithms/reduce.py
reikna/algorithms/scan.mako
reikna/algorithms/scan.py
reikna/algorithms/transpose.mako
reikna/algorithms/transpose.py
reikna/cbrng/__init__.py
reikna/cbrng/bijections.mako
reikna/cbrng/bijections.py
reikna/cbrng/cbrng.mako
reikna/cbrng/cbrng.py
reikna/cbrng/samplers.mako
reikna/cbrng/samplers.py
reikna/cbrng/tools.py
reikna/cluda/__init__.py
reikna/cluda/api.py
reikna/cluda/api_discovery.py
reikna/cluda/api_tools.py
reikna/cluda/array_helpers.py
reikna/cluda/cuda.py
reikna/cluda/dtypes.py
reikna/cluda/functions.mako
reikna/cluda/functions.py
reikna/cluda/kernel.mako
reikna/cluda/kernel.py
reikna/cluda/ocl.py
reikna/cluda/tempalloc.py
reikna/cluda/vsize.mako
reikna/cluda/vsize.py
reikna/core/__init__.py
reikna/core/computation.py
reikna/core/signature.py
reikna/core/transformation.py
reikna/core/transformation_modules.py
reikna/fft/__init__.py
reikna/fft/fft.mako
reikna/fft/fft.py
reikna/fft/fftshift.mako
reikna/fft/fftshift.py
reikna/helpers/__init__.py
