Metadata-Version: 2.1
Name: reikna
Version: 0.9.0
Summary: GPGPU algorithms for PyCUDA and PyOpenCL
Home-page: http://github.com/fjarri/reikna
Author: Bogdan Opanchuk
Author-email: bogdan@opanchuk.net
Classifier: Development Status :: 4 - Beta
Classifier: Intended Audience :: Science/Research
Classifier: Intended Audience :: Developers
Classifier: License :: OSI Approved :: MIT License
Classifier: Programming Language :: Python
Classifier: Programming Language :: Python :: 3
Classifier: Programming Language :: Python :: 3.8
Classifier: Topic :: Software Development
Classifier: Topic :: Scientific/Engineering
Classifier: Operating System :: OS Independent
Requires: mako(>= 1.0.0)
Requires: numpy(>= 2.0.0)
Requires: funcsigs(>= 1.0.0)
Provides: reikna
Provides-Extra: pyopencl
Provides-Extra: pycuda
Provides-Extra: dev
License-File: LICENSE.txt
